LICENSE
with_partial/__init__.py
with_partial/partial_context.py
with_partial/partial_proxy.py
with_partial-1.0.1.dist-info/LICENSE
with_partial-1.0.1.dist-info/WHEEL
with_partial-1.0.1.dist-info/METADATA
with_partial-1.0.1.dist-info/RECORD
